{"id":"us-029-purdue-university-m-s-in-computer-graphics-technology-hcdd","rank":29,"region":"US","country":"United States","school":"Purdue University","schoolCn":"普渡大学","short":"CGT","program":"M.S. in Computer Graphics Technology (HCDD)","programShort":"CGT","length":"2年","tuition":"约$23,000/年（州外）","location":"西拉法叶, IN","ielts":"IELTS 7.5","toefl":"TOEFL 90","gre":"需要","portfolio":"需要（4件最佳作品）","deadline":"2.1","academic":"3.0","stem":false,"stemNote":"未明确","website":"https://www.polytechnic.purdue.edu/degrees/ms-computer-graphics-technology","note":"【确认GRE恢复要求】Fall 2024起；【新增各项要求详情】","lastVerified":"2026-06-23","tags":["portfolio"],"_id":"program-us-029-purdue-university-m-s-in-computer-graphics-technology-hcdd","status":"published"}
